molecular_rectifier/__init__.py
molecular_rectifier/_base.py
molecular_rectifier/_odd.py
molecular_rectifier/_overclose.py
molecular_rectifier/_ring.py
molecular_rectifier/_valence.py
molecular_rectifier-0.1.6.dist-info/LICENSE
molecular_rectifier-0.1.6.dist-info/METADATA
molecular_rectifier-0.1.6.dist-info/WHEEL
molecular_rectifier-0.1.6.dist-info/top_level.txt
molecular_rectifier-0.1.6.dist-info/RECORD
