Metadata-Version: 2.1
Name: molecular_rectifier
Version: 0.1.6
Summary: Given an RDKit molecule that does not sanitise, correct it until it does, regardless of the severity of the change.
Home-page: https://github.com/matteoferla/molecular_rectifier
Author: Matteo Ferla
Author-email: matteo.ferla@gmail.com
License: MIT
Requires-Python: >3.6
License-File: LICENSE
